<channel>
	<item>
		<title>El rock de la pantalla</title>
		<pubDate>Fri, 10 Nov 2023 22:45:47 GMT</pubDate>
		<description>Unknown description</description>
		<link>https://www.pagina12.com.ar/615385-el-rock-de-la-pantalla</link>
	</item>
	<item>
		<title>Carlos Busqued, el escritor que tuiteaba anticipando el futuro</title>
		<pubDate>Sun, 05 Nov 2023 22:51:54 GMT</pubDate>
		<description>Unknown description</description>
		<link>https://www.pagina12.com.ar/613559-carlos-busqued-el-escritor-que-tuiteaba-anticipando-el-futur</link>
	</item>
	<item>
		<title>Gobernar tu tiempo</title>
		<pubDate>Mon, 30 Oct 2023 15:28:48 GMT</pubDate>
		<description>Unknown description</description>
		<link>https://www.pagina12.com.ar/611363-gobernar-tu-tiempo</link>
	</item>
	<item>
		<title>Italo Calvino: un amigo argentino y su elogio de la rebeldía y el 'no'</title>
		<pubDate>Mon, 23 Oct 2023 20:51:19 GMT</pubDate>
		<description>"El barón rampante" y la desobediencia en artistas y escritores como Keith Jarrett, Eduardo Galeano o Leila Guerriero.</description>
		<link>https://www.pagina12.com.ar/601129-italo-calvino-100-anos-de-amistad-con-argentina-y-el-poder-d</link>
	</item>
	<item>
		<title>El discurso de Meryl Streep al recibir el premio Princesa de Asturias</title>
		<pubDate>Sun, 22 Oct 2023 03:01:00 GMT</pubDate>
		<description>"Cuando nacemos nos identificamos con los demás, sentimos empatía. Los bebés lloran solo con ver las lágrimas de otro pero a medida que crecemos reprimimos esos sentimientos para suplantarlos a favor de una ideología o como un escudo. Y así llegamos a este triste momento de la Historia", expresó.</description>
		<link>https://www.pagina12.com.ar/600561-el-discurso-de-meryl-streep-al-recibir-el-premio-princesa-de</link>
	</item>
	<item>
		<title>El fantasma del influencer</title>
		<pubDate>Tue, 17 Oct 2023 01:38:35 GMT</pubDate>
		<description>Unknown description</description>
		<link>https://www.pagina12.com.ar/598913-el-fantasma-del-influencer</link>
	</item>
	<item>
		<title>Murió la poeta Louise Glück, Premio Nobel 2020</title>
		<pubDate>Fri, 13 Oct 2023 23:20:57 GMT</pubDate>
		<description>Unknown description</description>
		<link>https://www.pagina12.com.ar/598116-murio-la-poeta-louise-gluck-premio-nobel-2020</link>
	</item>
	<item>
		<title>Carburar con libertad Gamer</title>
		<pubDate>Fri, 06 Oct 2023 15:16:47 GMT</pubDate>
		<description>Unknown description</description>
		<link>https://www.pagina12.com.ar/595537-carburar-con-libertad-gamer</link>
	</item>
	<item>
		<title>Taylor Swift y los recitales más esperados para lo que queda del 2023</title>
		<pubDate>Sat, 30 Sep 2023 14:37:28 GMT</pubDate>
		<description>En los próximos meses también se presentan Rod Stewart, Red Hot Chili Pepper, Babasónicos y Tan Biónica, entre otros.</description>
		<link>https://www.pagina12.com.ar/530560-todos-los-recitales-y-shows-internacionales-en-argentina-par</link>
	</item>
	<item>
		<title>Cómo son las nuevas estampillas de colección del Correo Argentino con personajes de la cultura</title>
		<pubDate>Mon, 25 Sep 2023 03:10:29 GMT</pubDate>
		<description>El portal correocompras.com.ar revoluciona la venta de filatelia de colección a través de la oferta y venta virtual. El sello postal Homenaje a María Elena Walsh o el pack de estampillas del 35 Aniversario del Hospital Garrahan, son algunas de las muchas piezas de filatelia que ahora los argentinos pueden adquirir desde el portal de e-commerce de Correo Argentino.</description>
		<link>https://www.pagina12.com.ar/591554-como-son-las-nuevas-estampillas-de-coleccion-del-correo-arge</link>
	</item>
	<item>
		<title>Los ojos en el estado</title>
		<pubDate>Fri, 22 Sep 2023 20:55:54 GMT</pubDate>
		<description>Unknown description</description>
		<link>https://www.pagina12.com.ar/590870-los-ojos-en-el-estado</link>
	</item>
</channel>